azapi/__init__.py
azapi/azapi.py
azapi/jaro.py
azapi/requester.py
azapi/tools.py
azapi-3.0.8.dist-info/LICENSE
azapi-3.0.8.dist-info/METADATA
azapi-3.0.8.dist-info/WHEEL
azapi-3.0.8.dist-info/top_level.txt
azapi-3.0.8.dist-info/RECORD
