Metadata-Version: 2.1
Name: azapi
Version: 3.0.8
Summary: Get Lyrics from AZLyrics.com like a Boss ~(0_0)~
Home-page: https://github.com/elmoiv/azapi
Author: elmoiv
Author-email: elmoiv@yahoo.com
License: UNKNOWN
Platform: UNKNOWN
Classifier: Programming Language :: Python :: 3
Classifier: License :: OSI Approved :: GNU General Public License v3 (GPLv3)
Classifier: Operating System :: OS Independent
Requires-Python: >=3.4
